{"authorDailyContributionsMap":{"Ma-Yirui":[{"date":"2024-01-24","commitResults":[{"hash":"87c8f89ead9cdfeab5ef640fab3eddba4920a613","isMergeCommit":false,"messageTitle":"level0: initial skeleton code with greeting and exiting message","messageBody":"","tags":["Level-0"],"fileTypesAndContributionMap":{"java":{"insertions":21,"deletions":8}}}]},{"date":"2024-01-25","commitResults":[{"hash":"4e656c39a82fa65e239bf4f8284c3b7e3388a5e6","isMergeCommit":false,"messageTitle":"level-2: implemented echo","messageBody":"","tags":["Level-1"],"fileTypesAndContributionMap":{"java":{"insertions":29,"deletions":9}}},{"hash":"856de8eb8eab3f5e3df520514546771307482cd4","isMergeCommit":false,"messageTitle":"added indentation, implemented level-2 Add, List","messageBody":"","tags":["Level-2"],"fileTypesAndContributionMap":{"java":{"insertions":33,"deletions":11}}}]}]},"authorFileTypeContributionMap":{"Ma-Yirui":{"java":62,"md":0,"fxml":0,"sh":0,"bat":0,"gradle":0,"txt":0}},"authorContributionVariance":{"Ma-Yirui":829.2653},"authorDisplayNameMap":{"Ma-Yirui":"MA Y..IRUI"}}
