{"authorDailyContributionsMap":{"ReflectiveObsidian":[{"date":"2024-01-24","commitResults":[{"hash":"53af075fec256ebaba39943239918d592c2f8ac7","isMergeCommit":false,"messageTitle":"Replaced old greeting","messageBody":"","tags":["Level-0"],"fileTypesAndContributionMap":{"java":{"insertions":11,"deletions":6}}},{"hash":"d895b0a969739dca01fce03f9aa749a1277383cd","isMergeCommit":false,"messageTitle":"Implemented command echoing, with exit word.","messageBody":"","tags":["Level-1"],"fileTypesAndContributionMap":{"java":{"insertions":22,"deletions":4}}},{"hash":"1458d8681ecd4ddbcf3d3dcbf2e9a8009a607219","isMergeCommit":false,"messageTitle":"Add the ability to store whatever text entered by the user and display them back to the user when requested.","messageBody":"","tags":["Level-2"],"fileTypesAndContributionMap":{"java":{"insertions":16,"deletions":2}}},{"hash":"e515ca36e47fe6b5f03ed2e7447a10b7416e87ab","isMergeCommit":false,"messageTitle":"Moved to-do list into separate class","messageBody":"","fileTypesAndContributionMap":{"java":{"insertions":47,"deletions":42}}},{"hash":"bc6d49da7899f158d85f387e88674e7491af21e4","isMergeCommit":false,"messageTitle":"Added task class","messageBody":"","fileTypesAndContributionMap":{"java":{"insertions":18,"deletions":0}}},{"hash":"54e5c7d9f4f75ddba07d737448cabffcfaa9bbd9","isMergeCommit":false,"messageTitle":"Implement task status generation","messageBody":"","fileTypesAndContributionMap":{"java":{"insertions":8,"deletions":0}}},{"hash":"002be94f2d962d1856dbd129f1eac97b96072a00","isMergeCommit":false,"messageTitle":"Switch from list of string to list of Task in Pyrite","messageBody":"","tags":["A-Classes"],"fileTypesAndContributionMap":{"java":{"insertions":4,"deletions":4}}},{"hash":"020d7475e924c614c3092defee4fa211331998ab","isMergeCommit":false,"messageTitle":"Add the ability to mark tasks as done. Optionally, add the ability to change the status back to not done.","messageBody":"","fileTypesAndContributionMap":{"java":{"insertions":25,"deletions":8}}},{"hash":"9ea9232b051465f05f6f10bb5acc7fa43bf75ebb","isMergeCommit":false,"messageTitle":"Add \"Here are the tasks in your list:\" to task list printing","messageBody":"","fileTypesAndContributionMap":{"java":{"insertions":1,"deletions":0}}},{"hash":"a503c61ccec1b868ef9afafe98e4e9070bf9e559","isMergeCommit":false,"messageTitle":"Fixed off-by-1 bug in mark/unmark","messageBody":"","tags":["Level-3"],"fileTypesAndContributionMap":{"java":{"insertions":2,"deletions":2}}},{"hash":"c4e83cc271be3fa7eb0ad1cb2799781180d3036a","isMergeCommit":false,"messageTitle":"convert getFullStatusString into toString","messageBody":"","fileTypesAndContributionMap":{"java":{"insertions":3,"deletions":3}}},{"hash":"109216ccaaa0cbf282a3cee6e3b467a1dc87c732","isMergeCommit":false,"messageTitle":"override toString in Task instead of implementing getFullStatusString()","messageBody":"","fileTypesAndContributionMap":{"java":{"insertions":2,"deletions":1}}},{"hash":"44e29e4ce63bc6e1d668f31f075e240fd0be2e1b","isMergeCommit":false,"messageTitle":"Create 3 types of tasks, ToDo, Deadline, Event","messageBody":"","tags":["A-Inheritance"],"fileTypesAndContributionMap":{"java":{"insertions":38,"deletions":0}}},{"hash":"3f37747f4fe0129b9d7e50ec39e45930dd4c73af","isMergeCommit":false,"messageTitle":"Integrate ToDos, Deadlines, Events","messageBody":"","tags":["Level-4"],"fileTypesAndContributionMap":{"java":{"insertions":65,"deletions":5}}},{"hash":"75e780393c138c5ddc4a3073b05a34de0d02318d","isMergeCommit":false,"messageTitle":"fix indentation in mark/unmark","messageBody":"","fileTypesAndContributionMap":{"java":{"insertions":2,"deletions":2}}},{"hash":"d03061d58e3c57d2f34ff234c585c4bd5d4b86c7","isMergeCommit":false,"messageTitle":"Fix bug parsing event when order of parameters are swapped","messageBody":"","fileTypesAndContributionMap":{"java":{"insertions":2,"deletions":2}}},{"hash":"5e3769d2af794c478427ee4380cbdb2c62d81adb","isMergeCommit":false,"messageTitle":"Implemented Automated Testing","messageBody":"","tags":["A-TextUiTesting"],"fileTypesAndContributionMap":{"txt":{"insertions":9,"deletions":0}}},{"hash":"2466c5d7bc50709a94da145e0029943552ff0cef","isMergeCommit":false,"messageTitle":"Remove extra horizontal line from bye command","messageBody":"","fileTypesAndContributionMap":{"java":{"insertions":1,"deletions":2}}},{"hash":"3528784054af6f779ff3ea96879776bfad3554c7","isMergeCommit":false,"messageTitle":"Implement exception error handling.","messageBody":"","tags":["Level-5","A-Exceptions"],"fileTypesAndContributionMap":{"java":{"insertions":125,"deletions":65}}},{"hash":"412fc7ac86748550e797fa8208fdf58461349e15","isMergeCommit":false,"messageTitle":"Use ArrayList to store tasks","messageBody":"","tags":["A-Collections"],"fileTypesAndContributionMap":{"java":{"insertions":20,"deletions":24}}},{"hash":"3e8325093c9a9265bdce8b3d545fd1d5bdda17d2","isMergeCommit":false,"messageTitle":"Implement delete","messageBody":"","tags":["Level-6"],"fileTypesAndContributionMap":{"java":{"insertions":8,"deletions":0}}},{"hash":"b9eedd69f97635f4efeea03cbb42bd620ba8a996","isMergeCommit":false,"messageTitle":"Update test cases","messageBody":"","fileTypesAndContributionMap":{"txt":{"insertions":2,"deletions":0}}},{"hash":"e4dcd6de9542e6f7fa4865e32d0f3f071783d197","isMergeCommit":false,"messageTitle":"Use enums to track whether task is done or not","messageBody":"","tags":["A-Enums"],"fileTypesAndContributionMap":{"java":{"insertions":8,"deletions":4}}},{"hash":"a45fe4bcb9b8156e886f5c1cf9d4e238027e9f33","isMergeCommit":false,"messageTitle":"Make some variables in Pyrite static","messageBody":"","fileTypesAndContributionMap":{"java":{"insertions":5,"deletions":5}}}]},{"date":"2024-01-30","commitResults":[{"hash":"1298bbc6673ea5bc19b0d658df96f293680eb255","isMergeCommit":false,"messageTitle":"Add save to file feature","messageBody":"","fileTypesAndContributionMap":{"java":{"insertions":63,"deletions":1}}},{"hash":"4f32c4f0e823fb0f67ca97456fdd2a3e4c56d240","isMergeCommit":true,"messageTitle":"Merge branch \u0027branch-Level-7\u0027 into master","messageBody":"","tags":["Level-7"],"fileTypesAndContributionMap":{}},{"hash":"bc7c611b01ac1f77180a6bc791bd26e63833bc3a","isMergeCommit":false,"messageTitle":"Store dates as a java.time.LocalDateTime object in Task Objects","messageBody":"","fileTypesAndContributionMap":{"java":{"insertions":42,"deletions":19}}},{"hash":"7ca8f5d6fdf7ee208de30b021bbc2e630c97e402","isMergeCommit":true,"messageTitle":"Merge branch \u0027branch-Level-8\u0027 into master","messageBody":"","tags":["Level-8"],"fileTypesAndContributionMap":{}},{"hash":"4d6c582fd4163ba0223b5f8f854375d15c867e5f","isMergeCommit":false,"messageTitle":"Extract Task List into TaskList class","messageBody":"","fileTypesAndContributionMap":{"java":{"insertions":48,"deletions":18}}}]},{"date":"2024-01-31","commitResults":[{"hash":"956aaf9086c8c0894b3f989b3a8eb87af7050fdb","isMergeCommit":false,"messageTitle":"Refactor command handling out of the main loop, using classes Command and Parser","messageBody":"","fileTypesAndContributionMap":{"java":{"insertions":258,"deletions":179}}},{"hash":"ae0d92d3b3e42d22f2b2022f7b7b6cb989361dc8","isMergeCommit":false,"messageTitle":"Extract the UI class","messageBody":"","fileTypesAndContributionMap":{"java":{"insertions":34,"deletions":19}}},{"hash":"ba20ad6c1e88f475a6aaf415a383b01643d520f8","isMergeCommit":false,"messageTitle":"Move attribution for parser logic","messageBody":"","fileTypesAndContributionMap":{"java":{"insertions":3,"deletions":3}}},{"hash":"79593a15d2d9d1df9471d036a0955b02877af2a0","isMergeCommit":false,"messageTitle":"Remove unused variable","messageBody":"","fileTypesAndContributionMap":{"java":{"insertions":0,"deletions":1}}},{"hash":"3bd9915eae391cfcbc1b83c596e69bd4a2717db4","isMergeCommit":false,"messageTitle":"Fix bug in input checking during deletion","messageBody":"","tags":["A-MoreOOP"],"fileTypesAndContributionMap":{"java":{"insertions":1,"deletions":1}}},{"hash":"d1a6e7c424fedf53b474982d41873301d4c658c4","isMergeCommit":true,"messageTitle":"Merge tag \u0027A-MoreOOP\u0027 into master","messageBody":"","fileTypesAndContributionMap":{}},{"hash":"a794d6e326849fab13518bb1f4473f99d4293764","isMergeCommit":false,"messageTitle":"Organize into Packages","messageBody":"","tags":["A-Packages"],"fileTypesAndContributionMap":{"java":{"insertions":76,"deletions":13},"bat":{"insertions":1,"deletions":1},"md":{"insertions":2,"deletions":2}}},{"hash":"60ec1848f75fcefa91f07009d91be8dbbf424eb5","isMergeCommit":true,"messageTitle":"Merge branch \u0027add-gradle-support\u0027 into master","messageBody":"","tags":["A-Gradle"],"fileTypesAndContributionMap":{}}]},{"date":"2024-02-01","commitResults":[{"hash":"fc2cb7c9be723c21caebd859d0c253b7d4864952","isMergeCommit":false,"messageTitle":"Add dummy tests","messageBody":"","fileTypesAndContributionMap":{"java":{"insertions":16,"deletions":0}}},{"hash":"0f6a151071583b7735aaa0a9a73361533d2ede53","isMergeCommit":false,"messageTitle":"Add todoTest","messageBody":"","fileTypesAndContributionMap":{"java":{"insertions":28,"deletions":0}}},{"hash":"13382fc021ad1271a4e3f59f177a623cdeb6feb3","isMergeCommit":false,"messageTitle":"Add TaskListTest","messageBody":"","fileTypesAndContributionMap":{"java":{"insertions":38,"deletions":0}}},{"hash":"d98d3717c05f05f4c19a45b6896d0581e6da8f79","isMergeCommit":false,"messageTitle":"Extend TaskList tests","messageBody":"","fileTypesAndContributionMap":{"java":{"insertions":72,"deletions":2}}},{"hash":"43d6d89f1b9fbc1f8f0b5b3c6c236e2847d6453f","isMergeCommit":false,"messageTitle":"Add parser test","messageBody":"","fileTypesAndContributionMap":{"java":{"insertions":62,"deletions":0}}},{"hash":"cc9e63d5172cbf53d5bbaf139622d536794f319e","isMergeCommit":false,"messageTitle":"Update StatusCommand access parameters","messageBody":"","fileTypesAndContributionMap":{"java":{"insertions":1,"deletions":1}}},{"hash":"558a08977fd3c72b92cd5fbf573658ace30c2b53","isMergeCommit":true,"messageTitle":"Merge branch \u0027A-JUnit\u0027 into master","messageBody":"","tags":["A-JUnit"],"fileTypesAndContributionMap":{}},{"hash":"382f1e608167ccb8d86cebf06a0a233ac4e8c98a","isMergeCommit":false,"messageTitle":"Update build.gradle for jar creation","messageBody":"","tags":["A-Jar"],"fileTypesAndContributionMap":{"gradle":{"insertions":1,"deletions":1}}},{"hash":"089db79755eea4aff671b35c4e3a89728397f8e7","isMergeCommit":false,"messageTitle":"Add JavaDoc comments","messageBody":"","tags":["A-JavaDoc"],"fileTypesAndContributionMap":{"java":{"insertions":173,"deletions":0}}},{"hash":"edf816c5caf3fb12ef8357f2a13fae697d7f4c15","isMergeCommit":false,"messageTitle":"Comply with Naming coding standard","messageBody":"","tags":["A-CodingStandard"],"fileTypesAndContributionMap":{"java":{"insertions":20,"deletions":20}}},{"hash":"669526dfb98767ec636d7b969459027ed78d4365","isMergeCommit":false,"messageTitle":"Add find command","messageBody":"","tags":["Level-9"],"fileTypesAndContributionMap":{"java":{"insertions":32,"deletions":0}}},{"hash":"50e4df9c54b6ea74c0441d3bb4c461a7830ef9ed","isMergeCommit":true,"messageTitle":"Merge branch \u0027branch-A-JavaDoc\u0027 into master","messageBody":"","fileTypesAndContributionMap":{}},{"hash":"3e84d8d383467a9133bbb95cd166fbeb2bc614ef","isMergeCommit":true,"messageTitle":"Merge branch \u0027branch-A-CodingStandard\u0027 into master","messageBody":"# Conflicts:\n#\tsrc/main/java/pyrite/TaskList.java\n","fileTypesAndContributionMap":{}},{"hash":"6c44069f8278469faf89719e75f5d6ff7ceaf691","isMergeCommit":true,"messageTitle":"Merge branch \u0027branch-Level-9\u0027 into master","messageBody":"# Conflicts:\n#\tsrc/main/java/pyrite/TaskList.java\n","fileTypesAndContributionMap":{}}]},{"date":"2024-02-07","commitResults":[{"hash":"2b2198b9052370ab69b1d13a614bcd587fd5df10","isMergeCommit":false,"messageTitle":"Add GUI","messageBody":"","tags":["Level-10"],"fileTypesAndContributionMap":{"gradle":{"insertions":15,"deletions":0},"fxml":{"insertions":38,"deletions":0},"java":{"insertions":172,"deletions":69}}},{"hash":"3109fb9d63ddbec3567840ea25152b934bc1da88","isMergeCommit":true,"messageTitle":"Merge branch \u0027branch-Level-10\u0027 into master","messageBody":"","fileTypesAndContributionMap":{}},{"hash":"39f59f8878f0b13bf2ed9f5304583ea38f169939","isMergeCommit":false,"messageTitle":"Add and comply to checkstyle","messageBody":"","tags":["A-CheckStyle"],"fileTypesAndContributionMap":{"gradle":{"insertions":5,"deletions":0},"java":{"insertions":242,"deletions":155}}},{"hash":"7fe157254316ce46116ff5ca89cf96da6e0b1598","isMergeCommit":true,"messageTitle":"Merge branch \u0027branch-A-CheckStyle\u0027 into master","messageBody":"","fileTypesAndContributionMap":{}},{"hash":"937f3df08fa5aa635f7ed45e809593d0016b96bb","isMergeCommit":false,"messageTitle":"Add ability to parse multiple commands per user input","messageBody":"","tags":["A-Varargs"],"fileTypesAndContributionMap":{"java":{"insertions":21,"deletions":5}}},{"hash":"25c9ba17ccd3ccdb271e43af3aba59fc15ea3c75","isMergeCommit":true,"messageTitle":"Merge branch \u0027branch-A-Varargs\u0027 into master","messageBody":"","fileTypesAndContributionMap":{}}]},{"date":"2024-02-13","commitResults":[{"hash":"a2b2afc4795171d454b6bc0e90db8b5f12dc584e","isMergeCommit":false,"messageTitle":"Update build information","messageBody":"The class and method used to launch the program has\nchanged.\n\nThis change means that building the jar file does not produce a valid\nprogram.\n\nUpdating the Gradle configuration with the new names creates a working\njar.\n","tags":["A-FullCommitMessage"],"fileTypesAndContributionMap":{"gradle":{"insertions":1,"deletions":1}}},{"hash":"80f2f5f02282e82d62593d21e6f4a622db4d07b5","isMergeCommit":false,"messageTitle":"Update name of built file","messageBody":"","fileTypesAndContributionMap":{"gradle":{"insertions":1,"deletions":1}}},{"hash":"cdf0f792d12a81e3d192373deb0ee053e99fd84e","isMergeCommit":false,"messageTitle":"Use assert feature in StateFile and Task","messageBody":"There are no assertions in the code.\n\nAssertions document assumptions and surface incorrect ones.\n\nAdd assertions to points in the code where assumptions are being made.\n\nSeveral methods in StateFile and Task make assumptions about their input\nparameters, which should be documented.\n","tags":["A-Assertions"],"fileTypesAndContributionMap":{"java":{"insertions":3,"deletions":0}}},{"hash":"2a7e94bbf8badfa3a0b1dd9411e8f6b32302d831","isMergeCommit":false,"messageTitle":"Use streams to search for index of string in string array","messageBody":"A for loop is used to search for a string in an array.\n\nThis method is less readable because the happy path and intent to find\nthe index of the first occurring string is not clear.\n\nUse streams to search for the first occurrence of the string instead.\n\nThis way, the intent is clear and the default case of returning -1 is\nobvious.\n","fileTypesAndContributionMap":{"java":{"insertions":15,"deletions":6}}},{"hash":"b5761c0ff13c414fdf733bb680afa2c6d6e24099","isMergeCommit":false,"messageTitle":"Reduce nesting","messageBody":"","fileTypesAndContributionMap":{"java":{"insertions":98,"deletions":97}}},{"hash":"7f241fbd865a4c470bddcb8e1da83443d888e1e7","isMergeCommit":false,"messageTitle":"Move magic strings into named constants","messageBody":"","fileTypesAndContributionMap":{"java":{"insertions":18,"deletions":10}}},{"hash":"a2724d55b61e75205e8c9e3aeeb41289b84e0c60","isMergeCommit":true,"messageTitle":"Merge pull request #1 from ReflectiveObsidian/branch-A-Assertions","messageBody":"Use assert feature in StateFile and Task","fileTypesAndContributionMap":{}},{"hash":"a9793c8b8a474ea78052ed7b53f35a78a66d43ec","isMergeCommit":true,"messageTitle":"Merge pull request #2 from ReflectiveObsidian/branch-A-CodeQuality","messageBody":"Branch a code quality","fileTypesAndContributionMap":{}},{"hash":"70ce9abf9bb403c3fe16d269290272910a784b8c","isMergeCommit":true,"messageTitle":"Merge pull request #3 from ReflectiveObsidian/branch-A-Streams","messageBody":"Use streams to search for index of string in string array","fileTypesAndContributionMap":{}},{"hash":"6f61eb9cefac5ea08ef1311e07b7ea395faa6a9b","isMergeCommit":true,"messageTitle":"Merge branch \u0027master\u0027 into branch-A-Streams","messageBody":"","tags":["A-Streams"],"fileTypesAndContributionMap":{}},{"hash":"b12af75d40cd796313029648a055fcf52106b20e","isMergeCommit":false,"messageTitle":"Fix regression in find command that resulted in no results","messageBody":"","fileTypesAndContributionMap":{"java":{"insertions":3,"deletions":4}}},{"hash":"4bc921d8d4d197fbb2a649632b24969c2c70051a","isMergeCommit":false,"messageTitle":"Make find command case-insensitive","messageBody":"","tags":["C-BetterSearch","BCD-Extension"],"fileTypesAndContributionMap":{"java":{"insertions":3,"deletions":1}}}]},{"date":"2024-02-14","commitResults":[{"hash":"021cdfecf9245dae554488e3f70e62bae47c9e1e","isMergeCommit":true,"messageTitle":"Merge branch \u0027branch-A-CodeQuality\u0027 into master","messageBody":"","fileTypesAndContributionMap":{}}]},{"date":"2024-02-21","commitResults":[{"hash":"2c8c26b3ac4dbdebe07724f7298a9dd98d733ba0","isMergeCommit":false,"messageTitle":"Allow dialog box to expand with text","messageBody":"","fileTypesAndContributionMap":{"fxml":{"insertions":1,"deletions":1}}},{"hash":"51fd46fbbad8bb68ff3ecacf4031311691722b26","isMergeCommit":false,"messageTitle":"Reduce size of profile picture","messageBody":"","fileTypesAndContributionMap":{"fxml":{"insertions":1,"deletions":1}}},{"hash":"5fff788a5860ef8093de1c34aae46fefac77d0db","isMergeCommit":false,"messageTitle":"Change profile picture to circle shape","messageBody":"","fileTypesAndContributionMap":{"fxml":{"insertions":2,"deletions":2},"java":{"insertions":4,"deletions":3}}},{"hash":"d0e8fb56d458908f0fe595a9f2f5af0617d26098","isMergeCommit":false,"messageTitle":"Make window resizable","messageBody":"","fileTypesAndContributionMap":{"fxml":{"insertions":30,"deletions":10}}},{"hash":"16ca91164a90e338e1fadeba0c306f93146285ae","isMergeCommit":false,"messageTitle":"Remove extra newlines from responses","messageBody":"","tags":["A-BetterGui"],"fileTypesAndContributionMap":{"java":{"insertions":5,"deletions":2}}},{"hash":"29fd917223561a3967bc0a8eb656ab7ce249d0fe","isMergeCommit":false,"messageTitle":"Alter phrases","messageBody":"","tags":["A-Personality"],"fileTypesAndContributionMap":{"java":{"insertions":4,"deletions":4}}},{"hash":"ba3dd5813e3b4160f9ca4e896f2446854b40d223","isMergeCommit":false,"messageTitle":"Check if start date of event is after the end date","messageBody":"","tags":["A-MoreErrorHandling"],"fileTypesAndContributionMap":{"java":{"insertions":5,"deletions":0}}},{"hash":"efc35d701f0d4bc64eb769664434c73b0a4f538f","isMergeCommit":false,"messageTitle":"Add more testcases","messageBody":"","tags":["A-MoreTesting"],"fileTypesAndContributionMap":{"java":{"insertions":95,"deletions":0}}},{"hash":"b231bc772141d8e34b8b6ad17cea96b5542c2942","isMergeCommit":false,"messageTitle":"Add comments to denote use of Github Copilot in creating test cases","messageBody":"","tags":["A-AiAssisted"],"fileTypesAndContributionMap":{"java":{"insertions":8,"deletions":0}}},{"hash":"efe6fe597f8ea36f388f6cf917912d80626ddab7","isMergeCommit":false,"messageTitle":"Remove references to Duke","messageBody":"","fileTypesAndContributionMap":{"java":{"insertions":4,"deletions":4}}},{"hash":"9f1d35e66cf2515da7589478b238edae6d1d3fa7","isMergeCommit":false,"messageTitle":"Fix incorrect empty description test case","messageBody":"","fileTypesAndContributionMap":{"java":{"insertions":9,"deletions":6}}},{"hash":"51fa5df1689a046b2bbeb71150340a4ff24e2572","isMergeCommit":false,"messageTitle":"Fix dialog box text not aligning to right side for user dialog","messageBody":"","fileTypesAndContributionMap":{"fxml":{"insertions":1,"deletions":1}}},{"hash":"a7dcc22deb32891bad425bb6ac4f1c59bfcb1efc","isMergeCommit":false,"messageTitle":"Update README.md","messageBody":"","fileTypesAndContributionMap":{"md":{"insertions":4,"deletions":12}}},{"hash":"b0fdc56edffd94e4aaeee37f5edefc7f0d481749","isMergeCommit":false,"messageTitle":"Update README.md","messageBody":"","fileTypesAndContributionMap":{"md":{"insertions":86,"deletions":16}}},{"hash":"0cb75dc9135e567b381094750c6bdbb59aefce79","isMergeCommit":false,"messageTitle":"Update README.md to include link to user guide","messageBody":"","fileTypesAndContributionMap":{"md":{"insertions":4,"deletions":0}}},{"hash":"ca1756e3493ffbebecbaab672bd5fbc0b5ee4ea3","isMergeCommit":false,"messageTitle":"Update README.md","messageBody":"","fileTypesAndContributionMap":{"md":{"insertions":3,"deletions":6}}},{"hash":"414ea853d64dd2021f10b2e5197e42700495a25a","isMergeCommit":false,"messageTitle":"Update README.md to fix user guide link","messageBody":"","fileTypesAndContributionMap":{"md":{"insertions":1,"deletions":1}}},{"hash":"7f1ff3f9429ff471bfa9cd914bc2ac3f8aef9224","isMergeCommit":false,"messageTitle":"Update README.md","messageBody":"","tags":["A-UserGuide"],"fileTypesAndContributionMap":{"md":{"insertions":1,"deletions":11}}},{"hash":"8e010558c8060dc9a00ea2ae23adf41e63c729d5","isMergeCommit":false,"messageTitle":"Remove dummy tests","messageBody":"","fileTypesAndContributionMap":{"java":{"insertions":0,"deletions":18}}},{"hash":"0d03aa882b83468403799e2ea1e39cbe8cbefbd6","isMergeCommit":false,"messageTitle":"Add Javadoc to test cases","messageBody":"","fileTypesAndContributionMap":{"java":{"insertions":21,"deletions":1}}},{"hash":"e9d15368be24e48d84c97cd6eb279121522f50f1","isMergeCommit":false,"messageTitle":"UnknownCommandTest: Fix import style","messageBody":"","fileTypesAndContributionMap":{"java":{"insertions":1,"deletions":0}}},{"hash":"096343394dfa4d0617d6fe1a2bcd22ea9f80f745","isMergeCommit":false,"messageTitle":"Add error dialog box","messageBody":"","fileTypesAndContributionMap":{"java":{"insertions":32,"deletions":1}}},{"hash":"34a0372f96279ac1af41fb16a037d7be86a5c830","isMergeCommit":false,"messageTitle":"Refactor Parser","messageBody":"","fileTypesAndContributionMap":{"java":{"insertions":92,"deletions":112}}},{"hash":"d04c2410033ad6a26f1517066a7f6d43d874db4c","isMergeCommit":false,"messageTitle":"Update Parser test cases","messageBody":"","fileTypesAndContributionMap":{"java":{"insertions":10,"deletions":5}}},{"hash":"22d24b0883b8f1dd7576e01de12ca97a04ae7ec5","isMergeCommit":false,"messageTitle":"Update string access modifier in Parser","messageBody":"","fileTypesAndContributionMap":{"java":{"insertions":5,"deletions":5}}},{"hash":"dd67b261bf345f3ac3a0a8016c415c1697fcb852","isMergeCommit":false,"messageTitle":"Remove unused UnknownCommand","messageBody":"","fileTypesAndContributionMap":{"java":{"insertions":0,"deletions":55}}},{"hash":"5359741a83b5b9026de7d72e7d4651caef40a85c","isMergeCommit":false,"messageTitle":"Add javadocs to test cases","messageBody":"","fileTypesAndContributionMap":{"java":{"insertions":105,"deletions":0}}},{"hash":"91394ca3eb7132ca2b87479f6290b178ab77681a","isMergeCommit":false,"messageTitle":"Update README.md","messageBody":"","fileTypesAndContributionMap":{"md":{"insertions":31,"deletions":0}}},{"hash":"5fa7fee25bbebee30a130ac33d29f7f393a05597","isMergeCommit":false,"messageTitle":"Add more javadocs","messageBody":"","fileTypesAndContributionMap":{"java":{"insertions":76,"deletions":10}}},{"hash":"4915f3d35614a98ec542138ed91dd4343ebd8bb4","isMergeCommit":true,"messageTitle":"Merge branch \u0027master\u0027 of https://github.com/ReflectiveObsidian/ip into master","messageBody":"","fileTypesAndContributionMap":{}},{"hash":"a106f8b7f08474e1b4c26d2052e89ee0ab9b6543","isMergeCommit":false,"messageTitle":"Rename enum","messageBody":"","fileTypesAndContributionMap":{"java":{"insertions":17,"deletions":17}}},{"hash":"e4560a5bb898858c8dc1bea8344f6a1494ebfca6","isMergeCommit":false,"messageTitle":"Fix wrong import orders","messageBody":"","fileTypesAndContributionMap":{"java":{"insertions":4,"deletions":4}}},{"hash":"ed5730cf02e1f122b03e433c40d8103c2b97dbef","isMergeCommit":false,"messageTitle":"Fix incorrect error message","messageBody":"","fileTypesAndContributionMap":{"java":{"insertions":1,"deletions":1}}},{"hash":"789cf40fed70d94160f31626ec3725b7868396f6","isMergeCommit":false,"messageTitle":"Update command list in error message","messageBody":"","tags":["A-Release"],"fileTypesAndContributionMap":{"java":{"insertions":1,"deletions":1}}}]}]},"authorFileTypeContributionMap":{"ReflectiveObsidian":{"java":1434,"md":111,"fxml":58,"sh":0,"bat":1,"gradle":22,"txt":11}},"authorContributionVariance":{"ReflectiveObsidian":61884.39},"authorDisplayNameMap":{"ReflectiveObsidian":"CS2103T-T11-1 NG W..MING"}}
