{"authorDailyContributionsMap":{"bachletuankhai":[{"date":"2024-01-24","commitResults":[{"hash":"98f0cceae3a7d6f02640996dd90667088ad99a13","isMergeCommit":false,"messageTitle":"Change name to Sylvia, add greetings and exit lines","messageBody":"","tags":["Level-0"],"fileTypesAndContributionMap":{"java":{"insertions":4,"deletions":6}}}]},{"date":"2024-01-25","commitResults":[{"hash":"2f1d4f776095410bac1e833242bbc0724ad7cee8","isMergeCommit":false,"messageTitle":"Add greet() and exit() methods","messageBody":"","fileTypesAndContributionMap":{"java":{"insertions":13,"deletions":2}}},{"hash":"44bd28e5ed6eee78861a0890150ad9de9ea23cf6","isMergeCommit":false,"messageTitle":"Add quit functionality and echo user input","messageBody":"","tags":["Level-1"],"fileTypesAndContributionMap":{"java":{"insertions":36,"deletions":1}}},{"hash":"daf9131d2303c42e6ccbf6a6bcbe2d43944d2fe1","isMergeCommit":false,"messageTitle":"Replace static methods with non-static; add adding and listing items feature","messageBody":"","tags":["Level-2"],"fileTypesAndContributionMap":{"java":{"insertions":66,"deletions":42}}},{"hash":"631b47e314f9f702fa83accf6ecd7595ed8631c2","isMergeCommit":false,"messageTitle":"Add Task and TaskList classes","messageBody":"","fileTypesAndContributionMap":{"java":{"insertions":58,"deletions":0}}},{"hash":"4beaa27623b9fef8fe5a709c14e997be36c41e39","isMergeCommit":false,"messageTitle":"Add adding and mark/unmarking tasks function","messageBody":"","tags":["Level-3"],"fileTypesAndContributionMap":{"java":{"insertions":42,"deletions":11}}}]}]},"authorFileTypeContributionMap":{"bachletuankhai":{"java":163,"md":0,"fxml":0,"sh":0,"bat":0,"gradle":0,"txt":0}},"authorContributionVariance":{"bachletuankhai":8894.408},"authorDisplayNameMap":{"bachletuankhai":"BACH..KHAI"}}
