{"authorDailyContributionsMap":{"IamZhenHong":[{"date":"2024-01-31","commitResults":[{"hash":"b2a586c7be5f0ebc3ea48c002c0f4bbda4df7459","isMergeCommit":false,"messageTitle":"Initial implementation of CharmBot with greeting and exit","messageBody":"","tags":["Level-0"],"fileTypesAndContributionMap":{"java":{"insertions":6,"deletions":0}}},{"hash":"943d23f9dc2a870bfd476a5f6b62b9b75df41f7f","isMergeCommit":false,"messageTitle":"Enhance Charmbot to echo user commands and exit on bye","messageBody":"","tags":["Level-1"],"fileTypesAndContributionMap":{"java":{"insertions":13,"deletions":1}}},{"hash":"07440836d70fd92304bc32bc04000a4a74f799ea","isMergeCommit":false,"messageTitle":"Add text storage and display functionality to CharmBot","messageBody":"","tags":["Level-2"],"fileTypesAndContributionMap":{"java":{"insertions":13,"deletions":1}}}]},{"date":"2024-02-05","commitResults":[{"hash":"3788eb8f8f25ae8f23a6904a9ac37b6274c75898","isMergeCommit":false,"messageTitle":"Added mark and unmark functionality to Charmbot","messageBody":"","tags":["Level-3"],"fileTypesAndContributionMap":{"java":{"insertions":45,"deletions":3}}},{"hash":"0e044fd85f090ef03907f92cea843a6fd28c4593","isMergeCommit":false,"messageTitle":"Added Todos,Events,Deadlines tracking for CharmBot","messageBody":"","tags":["Level-4"],"fileTypesAndContributionMap":{"java":{"insertions":74,"deletions":5}}},{"hash":"b8eff85be8f8168ed91134ba6e45a7f6d17d8b7b","isMergeCommit":false,"messageTitle":"Added Automated Test UI Testing","messageBody":"","tags":["A-TestUiTesting"],"fileTypesAndContributionMap":{"bat":{"insertions":0,"deletions":21},"sh":{"insertions":0,"deletions":0}}},{"hash":"b9b266de456f9f7c70176491fdd969e09ec4b991","isMergeCommit":false,"messageTitle":"Added exceptions to handle input errors","messageBody":"","fileTypesAndContributionMap":{"java":{"insertions":103,"deletions":56}}}]},{"date":"2024-02-06","commitResults":[{"hash":"ac52d323a237416902eacf70e467cb8e0967f239","isMergeCommit":false,"messageTitle":"Added error handling functionality to CharmBot","messageBody":"","tags":["Level-5"],"fileTypesAndContributionMap":{"java":{"insertions":86,"deletions":101}}},{"hash":"a229714de6a1a833cf25c4b13026d3617cffbd55","isMergeCommit":false,"messageTitle":"Added support for deleting tasks from list","messageBody":"","tags":["Level-6"],"fileTypesAndContributionMap":{"java":{"insertions":29,"deletions":23}}}]},{"date":"2024-02-07","commitResults":[{"hash":"be64ce0acf53211f8b6daad9b3ff0c6e960e6ce1","isMergeCommit":false,"messageTitle":"Enabling saving and loading data with hard disk","messageBody":"","fileTypesAndContributionMap":{"txt":{"insertions":3,"deletions":0},"java":{"insertions":86,"deletions":2}}},{"hash":"7fa2323fa7dc4c2d52317a58fc0a721fe4e3c0de","isMergeCommit":true,"messageTitle":"Merge branch \u0027branch-Level-7df into main","messageBody":"","tags":["Level-7"],"fileTypesAndContributionMap":{}}]}]},"authorFileTypeContributionMap":{"IamZhenHong":{"java":261,"md":0,"fxml":0,"sh":0,"bat":0,"gradle":0,"txt":3}},"authorContributionVariance":{"IamZhenHong":6914.7476},"authorDisplayNameMap":{"IamZhenHong":"CS2103T-W10-3 SENG..HONG"}}
