{"authorDailyContributionsMap":{"tahsinhasem":[{"date":"2024-02-06","commitResults":[{"hash":"e7052e07e562e7b718bcf72e2a5357c122eef4c0","isMergeCommit":false,"messageTitle":"Renamed duke to dude, added greet and bye","messageBody":"","tags":["level-0","Level-0"],"fileTypesAndContributionMap":{"java":{"insertions":34,"deletions":10}}},{"hash":"0232b97ce95345e477fb5b2cb2f6b41bacf291d3","isMergeCommit":false,"messageTitle":"Added echo feature, added indentation to responses","messageBody":"","tags":["level-1","Level-1"],"fileTypesAndContributionMap":{"java":{"insertions":31,"deletions":8}}},{"hash":"6655cdb376e2376ac259b45255690563d86cfbab","isMergeCommit":false,"messageTitle":"Added TaskList.java, Implemented Adding Tasks","messageBody":"","tags":["Level-2"],"fileTypesAndContributionMap":{"java":{"insertions":60,"deletions":7}}},{"hash":"8f5c5b69e598c5c4e4eac3d21460577d98b2c152","isMergeCommit":false,"messageTitle":"Changed Logo","messageBody":"","fileTypesAndContributionMap":{"java":{"insertions":11,"deletions":6}}},{"hash":"cface250f0b4410314304ae28323c623d7946f4b","isMergeCommit":false,"messageTitle":"Added Task.java","messageBody":"","fileTypesAndContributionMap":{"java":{"insertions":30,"deletions":0}}},{"hash":"a8e470ae734eec58f16a8d8aa779f3a27a64be3e","isMergeCommit":false,"messageTitle":"Refactored Task List to work with Task objects instead of Strings","messageBody":"","fileTypesAndContributionMap":{"java":{"insertions":7,"deletions":5}}},{"hash":"198fa53d2189a3aca90909d1e3714ed79414934e","isMergeCommit":false,"messageTitle":"Refactored TaskList to throw errors","messageBody":"","fileTypesAndContributionMap":{"java":{"insertions":43,"deletions":7}}},{"hash":"cce34ff063d1a463cac30faa557397bf1a208434","isMergeCommit":false,"messageTitle":"Changed TaskListFullException to be public","messageBody":"","fileTypesAndContributionMap":{"java":{"insertions":1,"deletions":1}}},{"hash":"19b40a536ebc5b816e0e7953d9bcd5f7bc41bad1","isMergeCommit":false,"messageTitle":"Renamed variable s to msg","messageBody":"","fileTypesAndContributionMap":{"java":{"insertions":3,"deletions":6}}},{"hash":"397c9b187ac4f12a4842cc1209bb06770d4eb634","isMergeCommit":false,"messageTitle":"Added mark_ as done feature","messageBody":"","fileTypesAndContributionMap":{"java":{"insertions":23,"deletions":5}}},{"hash":"51ede74c8b0521e37649500f890c3637154f50a5","isMergeCommit":false,"messageTitle":"Changed the output message to include task number for marking and unmarking tasks","messageBody":"","fileTypesAndContributionMap":{"java":{"insertions":2,"deletions":2}}},{"hash":"90ce70dc1766d74d28641987d19b705b080a7125","isMergeCommit":false,"messageTitle":"Added Unmark Feature","messageBody":"","fileTypesAndContributionMap":{"java":{"insertions":24,"deletions":0}}},{"hash":"6ecac320f69d437d2e50d065bc688124bdaaad2a","isMergeCommit":false,"messageTitle":"Added handling case for empty input - \"\".","messageBody":"","tags":["Level-3"],"fileTypesAndContributionMap":{"java":{"insertions":7,"deletions":0}}},{"hash":"8ba0809134276d4ed7da3533845183b299dbfb79","isMergeCommit":false,"messageTitle":"Added Todo class","messageBody":"","fileTypesAndContributionMap":{"java":{"insertions":21,"deletions":0}}},{"hash":"a2106edb7a596d08be71d3db0db239f2bafe4885","isMergeCommit":false,"messageTitle":"Added Deadline class","messageBody":"","fileTypesAndContributionMap":{"java":{"insertions":24,"deletions":0}}},{"hash":"354d0f46dae8a1b29f8dd298c7c0d4aa3cd4840f","isMergeCommit":false,"messageTitle":"Added Event class","messageBody":"","fileTypesAndContributionMap":{"java":{"insertions":17,"deletions":0}}}]}]},"authorFileTypeContributionMap":{"tahsinhasem":{"java":291,"md":0,"fxml":0,"sh":0,"bat":0,"gradle":0,"txt":0}},"authorContributionVariance":{"tahsinhasem":7779.639},"authorDisplayNameMap":{"tahsinhasem":"CS2103T-W08-3 AONI..ASEM"}}
